eve/__init__.py
eve/config.py
eve/core.py
eve_bus-0.1.2.dist-info/licenses/LICENSE
eve_bus-0.1.2.dist-info/METADATA
eve_bus-0.1.2.dist-info/WHEEL
eve_bus-0.1.2.dist-info/top_level.txt
eve_bus-0.1.2.dist-info/RECORD
