Metadata-Version: 2.4
Name: eve-bus
Version: 0.1.2
Summary: A lightweight event bus implementation using Redis
Home-page: https://github.com/DotNetAge/eve-bus
Author: Ray
Author-email: Ray <ray@rayainfo.cn>
License-Expression: MIT
Project-URL: Homepage, https://github.com/DotNetAge/eve-bus
Project-URL: Bug Tracker, https://github.com/DotNetAge/eve-bus/issues
Classifier: Programming Language :: Python :: 3
Classifier: Operating System :: OS Independent
Requires-Python: >=3.8
License-File: LICENSE
Requires-Dist: redis>=5.0.0
Requires-Dist: pydantic>=2.0.0
Requires-Dist: dependency-injector>=4.41.0
Requires-Dist: python-dotenv>=1.0.1
Provides-Extra: dev
Dynamic: author
Dynamic: home-page
Dynamic: license-file
Dynamic: requires-python
